gophr_bridge/__init__.py
gophr_bridge/client.py
gophr_bridge/py.typed
gophr_bridge_sdk-1.0.10.dist-info/licenses/LICENSE
gophr_bridge_sdk-1.0.10.dist-info/METADATA
gophr_bridge_sdk-1.0.10.dist-info/WHEEL
gophr_bridge_sdk-1.0.10.dist-info/top_level.txt
gophr_bridge_sdk-1.0.10.dist-info/RECORD
